setup.py
bobsleigh_seddonym/__init__.py
bobsleigh_seddonym.egg-info/PKG-INFO
bobsleigh_seddonym.egg-info/SOURCES.txt
bobsleigh_seddonym.egg-info/dependency_links.txt
bobsleigh_seddonym.egg-info/top_level.txt
bobsleigh_seddonym/handlers/__init__.py
bobsleigh_seddonym/handlers/local.py
bobsleigh_seddonym/handlers/webfaction.py
bobsleigh_seddonym/settings/__init__.py
bobsleigh_seddonym/settings/base.py