Metadata-Version: 1.0
Name: bobsleigh-seddonym
Version: 0.1.4
Summary: Helpful Bobsleigh settings for my projects.
Home-page: http://github.com/seddonym/bobsleigh-seddonym/
Author: David Seddon
Author-email: david@seddonym.me
License: UNKNOWN
Platform: UNKNOWN
